<?xml version="1.0" encoding="UTF-8"?>
<configuration debug="false">
    <!--<property name="LOG_FILE" value="${java.io.tmpdir}/crs.log" />-->
    <include resource="org/springframework/boot/logging/logback/defaults.xml" />
    <include resource="org/springframework/boot/logging/logback/console-appender.xml" />
    <!--<include resource="org/springframework/boot/logging/logback/file-appender.xml" />-->
    <!--Loggers...-->
    <logger name="com.aysoft.onionproject" level="DEBUG" additivity="false">
        <appender-ref ref="CONSOLE" />
    </logger>
    <root level="INFO">
        <appender-ref ref="CONSOLE" />
    </root>
</configuration>